{"@context":"https://iiif.io/api/presentation/3/context.json","id":"https://wuschlor.github.io/demo-canopy-iiif/api/facet/composer/rogovoy-g.json","type":"Collection","label":{"none":["Rogovoy, G."]},"items":[{"id":"https://cdm16786.contentdm.oclc.org/iiif/sm:672/manifest.json","type":"Manifest","label":{"none":["Waltz Seattle"]},"thumbnail":[{"id":"https://cdm16786.contentdm.oclc.org/iiif/2/sm:617/full/400,/0/default.jpg","type":"Image","format":"image/jpeg","width":400,"height":529}],"homepage":[{"id":"https://wuschlor.github.io/demo-canopy-iiif/works/waltz-seattle","type":"Text","label":{"none":["Waltz Seattle"]}}]}],"partOf":[{"id":"https://wuschlor.github.io/demo-canopy-iiif/api/facet/composer.json","type":"Collection"}],"summary":{"none":["Composer"]},"homepage":[{"id":"https://wuschlor.github.io/demo-canopy-iiif/search?composer=rogovoy-g","type":"Text","label":{"none":["Rogovoy, G."]}}]}