{"@context":"https://iiif.io/api/presentation/3/context.json","id":"https://wuschlor.github.io/demo-canopy-iiif/api/facet/composer/weeks-harold-1893-1967-casey-james-w.json","type":"Collection","label":{"none":["Weeks, Harold, 1893-1967\nCasey, James W."]},"items":[{"id":"https://cdm16786.contentdm.oclc.org/iiif/sm:686/manifest.json","type":"Manifest","label":{"none":["You ought to know"]},"thumbnail":[{"id":"https://cdm16786.contentdm.oclc.org/iiif/2/sm:683/full/400,/0/default.jpg","type":"Image","format":"image/jpeg","width":400,"height":544}],"homepage":[{"id":"https://wuschlor.github.io/demo-canopy-iiif/works/you-ought-to-know","type":"Text","label":{"none":["You ought to know"]}}]}],"partOf":[{"id":"https://wuschlor.github.io/demo-canopy-iiif/api/facet/composer.json","type":"Collection"}],"summary":{"none":["Composer"]},"homepage":[{"id":"https://wuschlor.github.io/demo-canopy-iiif/search?composer=weeks-harold-1893-1967-casey-james-w","type":"Text","label":{"none":["Weeks, Harold, 1893-1967\nCasey, James W."]}}]}